ztm_buses/BusStatistician.py
ztm_buses/Visualizer.py
ztm_buses/ZTMFetcher.py
ztm_buses/__init__.py
ztm_buses/modules/Bus.py
ztm_buses/modules/BusStopsManager.py
ztm_buses/modules/Coordinates.py
ztm_buses/modules/PunctualityAnalyzer.py
ztm_buses/modules/RoutesManager.py
ztm_buses/modules/SpeedAnalyzer.py
ztm_buses/modules/TimetableManager.py
ztm_buses/modules/__init__.py
ztm_buses/modules/time_changer.py
ztm_buses-0.0.1.dist-info/LICENSE
ztm_buses-0.0.1.dist-info/METADATA
ztm_buses-0.0.1.dist-info/WHEEL
ztm_buses-0.0.1.dist-info/top_level.txt
ztm_buses-0.0.1.dist-info/RECORD
