Metadata-Version: 2.1
Name: ztm-buses
Version: 0.0.1
Summary: Warsaw ZTM API Fetcher and Data Analyzer
Home-page: https://github.com/MMax337/ztm_buses/tree/main
Author: Maksym Matviienko
Author-email: xxxmax337@example.com
Classifier: Programming Language :: Python :: 3
Classifier: License :: OSI Approved :: MIT License
Classifier: Operating System :: OS Independent
Requires-Python: >=3.6
License-File: LICENSE
Requires-Dist: requests
Requires-Dist: urllib3
Requires-Dist: folium
Requires-Dist: plotly-express
Requires-Dist: pandas
